django_etna/auth/legacy_auth.py
django_etna/auth/test.py
django_etna/auth/user.py
django_etna/auth/utils.py
django_etna/test/__init__.py
django_etna-1.1.2.dist-info/METADATA
django_etna-1.1.2.dist-info/WHEEL
django_etna-1.1.2.dist-info/top_level.txt
django_etna-1.1.2.dist-info/RECORD
