Metadata-Version: 2.1
Name: django-etna
Version: 1.1.2
Summary: Django middlewares and helpers for ETNA
Home-page: https://github.com/etna-alternance/django_etna
Author: Arthur CROS
Author-email: arthur.cros@etna.io
License: UNKNOWN
Platform: UNKNOWN
Classifier: Programming Language :: Python :: 3
Classifier: License :: OSI Approved :: MIT License
Classifier: Operating System :: OS Independent
Requires-Dist: django
Requires-Dist: jinja2
Requires-Dist: pyopenssl
Requires-Dist: redgreenunittest
Requires-Dist: requests
Requires-Dist: whitenoise
